score.kvcache-0.2.2-py3.4-nspkg.pth
score/kvcache/__init__.py
score/kvcache/_container.py
score/kvcache/_init.py
score/kvcache/backend.py
score.kvcache-0.2.2.dist-info/DESCRIPTION.rst
score.kvcache-0.2.2.dist-info/METADATA
score.kvcache-0.2.2.dist-info/RECORD
score.kvcache-0.2.2.dist-info/WHEEL
score.kvcache-0.2.2.dist-info/metadata.json
score.kvcache-0.2.2.dist-info/namespace_packages.txt
score.kvcache-0.2.2.dist-info/top_level.txt
